pysensibo/__init__.py
pysensibo/exceptions.py
pysensibo/model.py
pysensibo/py.typed
pysensibo-1.2.0.dist-info/LICENSE
pysensibo-1.2.0.dist-info/METADATA
pysensibo-1.2.0.dist-info/WHEEL
pysensibo-1.2.0.dist-info/RECORD
