Metadata-Version: 2.1
Name: pysensibo
Version: 1.2.0
Summary: asyncio-friendly python API for Sensibo
Home-page: https://github.com/andrey-git/pysensibo
License: MIT
Keywords: sensibo,api,async,client
Author: G Johansson
Author-email: goran.johansson@shiftit.se
Maintainer: G Johansson
Maintainer-email: goran.johansson@shiftit.se
Requires-Python: >=3.11,<4.0
Classifier: Development Status :: 5 - Production/Stable
Classifier: Intended Audience :: Developers
Classifier: License :: OSI Approved :: MIT License
Classifier: Natural Language :: English
Classifier: Programming Language :: Python :: 3
Classifier: Programming Language :: Python :: 3.11
Classifier: Programming Language :: Python :: 3.12
Classifier: Programming Language :: Python :: 3.13
Classifier: Topic :: Software Development :: Libraries :: Python Modules
Requires-Dist: aiohttp (>=3.10,<4.0)
Project-URL: Bug Tracker, https://github.com/andrey-git/pysensibo/issues
Project-URL: Changelog, https://github.com/andrey-git/pysensibo/releases
Project-URL: Documentation, https://github.com/andrey-git/pysensibo
Project-URL: Repository, https://github.com/andrey-git/pysensibo
